tensorcom/__init__.py
tensorcom/tenbin.py
tensorcom/zcom.py
tensorcom-0.1.0.data/scripts/serve-imagenet-dir
tensorcom-0.1.0.data/scripts/serve-imagenet-shards
tensorcom-0.1.0.data/scripts/tensormon
tensorcom-0.1.0.data/scripts/tensorshow
tensorcom-0.1.0.data/scripts/tensorstat
tensorcom-0.1.0.dist-info/LICENSE
tensorcom-0.1.0.dist-info/METADATA
tensorcom-0.1.0.dist-info/WHEEL
tensorcom-0.1.0.dist-info/top_level.txt
tensorcom-0.1.0.dist-info/RECORD
