Metadata-Version: 2.1
Name: tensorcom
Version: 0.1.0
Summary: Distributed preprocessing for deep learning.
Home-page: http://github.com/tmbdev/tensorcom
Author: Thomas Breuel
Author-email: tmbdev+removeme@gmail.com
License: MIT
Keywords: object store,client,deep learning
Platform: UNKNOWN
Classifier: Development Status :: 3 - Alpha
Classifier: License :: OSI Approved :: BSD License
Classifier: Programming Language :: Python :: 3.6
Classifier: Programming Language :: Python :: 3.7
Requires-Python: >=3.6
Requires-Dist: msgpack
Requires-Dist: pyzmq
Requires-Dist: torch
Requires-Dist: webdataset
